Adafruit_I2C.py
KalmanFilter.py
adxl345.py
chainable_rgb_direct.py
dextergps.py
grove_128_64_oled.py
grove_barometer_lib.py
grove_co2_lib.py
grove_compass_lib.py
grove_dht.py
grove_gesture_sensor.py
grove_hightemperature_sensor.py
grove_i2c_adc.py
grove_i2c_barometic_sensor_BMP180.py
grove_i2c_color_sensor.py
grove_i2c_motor_driver.py
grove_i2c_temp_hum_hdc1000.py
grove_i2c_temp_hum_mini.py
grove_mini_motor_driver.py
grove_oled.py
grove_rflink433mhz.py
grove_rgb_lcd.py
grovepi.py
hp206c.py
lsm303d.py
multichannel_gas_sensor.py
grovepi-1.0.4.dist-info/METADATA
grovepi-1.0.4.dist-info/RECORD
grovepi-1.0.4.dist-info/WHEEL
grovepi-1.0.4.dist-info/top_level.txt
